odoo/addons/l10n_ro_stock_picking_comment_template/README.rst
odoo/addons/l10n_ro_stock_picking_comment_template/__init__.py
odoo/addons/l10n_ro_stock_picking_comment_template/__manifest__.py
odoo/addons/l10n_ro_stock_picking_comment_template/data/l10n_ro_stock_picking_comment_template.xml
odoo/addons/l10n_ro_stock_picking_comment_template/i18n/l10n_ro_stock_picking_comment_template.pot
odoo/addons/l10n_ro_stock_picking_comment_template/i18n/ro.po
odoo/addons/l10n_ro_stock_picking_comment_template/models/__init__.py
odoo/addons/l10n_ro_stock_picking_comment_template/models/res_partner.py
odoo/addons/l10n_ro_stock_picking_comment_template/models/stock_picking.py
odoo/addons/l10n_ro_stock_picking_comment_template/readme/CONTRIBUTORS.md
odoo/addons/l10n_ro_stock_picking_comment_template/readme/DESCRIPTION.md
odoo/addons/l10n_ro_stock_picking_comment_template/readme/USAGE.md
odoo/addons/l10n_ro_stock_picking_comment_template/security/ir.model.access.csv
odoo/addons/l10n_ro_stock_picking_comment_template/static/description/icon.png
odoo/addons/l10n_ro_stock_picking_comment_template/static/description/icon.svg
odoo/addons/l10n_ro_stock_picking_comment_template/static/description/index.html
odoo/addons/l10n_ro_stock_picking_comment_template/views/base_comment_template_view.xml
odoo/addons/l10n_ro_stock_picking_comment_template/views/report_delivery_document.xml
odoo/addons/l10n_ro_stock_picking_comment_template/views/report_picking.xml
odoo/addons/l10n_ro_stock_picking_comment_template/views/stock_picking_view.xml
odoo_addon_l10n_ro_stock_picking_comment_template-18.0.0.2.0.dist-info/METADATA
odoo_addon_l10n_ro_stock_picking_comment_template-18.0.0.2.0.dist-info/WHEEL
odoo_addon_l10n_ro_stock_picking_comment_template-18.0.0.2.0.dist-info/top_level.txt
odoo_addon_l10n_ro_stock_picking_comment_template-18.0.0.2.0.dist-info/RECORD
