Metadata-Version: 2.1
Name: odoo-addon-l10n_ro_stock_picking_comment_template
Version: 18.0.0.2.0
Requires-Python: >=3.10
Requires-Dist: odoo-addon-base_comment_template==18.0.*
Requires-Dist: odoo-addon-l10n_ro_stock_account==18.0.*
Requires-Dist: odoo==18.0.*
Summary: This model is going to add a a header and a footer at picking report depeding on the operation type.
Home-page: https://github.com/OCA/l10n-romania
License: AGPL-3
Author: NextERP Romania,Odoo Community Association (OCA)
Author-email: support@odoo-community.org
Classifier: Programming Language :: Python
Classifier: Framework :: Odoo
Classifier: Framework :: Odoo :: 18.0
Classifier: License :: OSI Approved :: GNU Affero General Public License v3
Classifier: Development Status :: 4 - Beta
